[
  {
    "id": 39,
    "type": "Bán",
    "title": "bán nhà phố quận 2",
    "slug": "ban-nha-pho-quan-2",
    "cat": "ban-nha-pho-quan-2",
    "projectCode": "an-phu-new-city",
    "loc": "an phú",
    "price": "15 tỷ",
    "area": "145 m",
    "bed": "",
    "img": "https://images.unsplash.com/photo-1600596542815-ffad4c1539a9?w=800",
    "gallery": [
      "https://images.unsplash.com/photo-1600596542815-ffad4c1539a9?w=800"
    ],
    "content": "<div style=\"background:#f9f9f9; padding:15px; border-left:4px solid #c5a059; margin:20px 0;\"><strong>👉 Xem chi tiết:</strong> <a href=\"https://mrliga1.github.io/greenia-homes/san-pham/undefined/\" style=\"color:#c5a059; font-weight:bold; text-decoration:none;\">bán nhà phố quận 2</a></div>",
    "seoTitle": "bán nhà phố quận 2",
    "seoDesc": "👉 Xem chi tiết: bán nhà phố quận 2...",
    "seoKeywords": "ban-nha-pho-quan-2, bất động sản"
  },
  {
    "id": 10,
    "title": "bán nhà",
    "img": "https://mrliga1.github.io/greenia-homes/bai-viet/kiem-tra-dang-bai-viet/",
    "gallery": [
      "https://mrliga1.github.io/greenia-homes/bai-viet/kiem-tra-dang-bai-viet/"
    ],
    "price": "10 tỷ",
    "area": "100 m2",
    "bed": "4 PN",
    "wc": "",
    "direction": "",
    "floor": "",
    "front": "",
    "legal": "",
    "loc": "an phú",
    "type": "Bán",
    "cat": "nha-pho-quan-2",
    "catName": "nhà phố quận 2",
    "projectCode": "the-global-city",
    "desc": "<p> kiểm tra sản phẩm</p>",
    "map": ""
  },
  {
    "id": 1,
    "title": "Biệt thự ven sông The Global City",
    "img": "https://images.unsplash.com/photo-1600596542815-ffad4c1539a9?w=800",
    "gallery": [
      "https://images.unsplash.com/photo-1600596542815-ffad4c1539a9?w=1200"
    ],
    "price": "45 Tỷ",
    "area": "320",
    "bed": "4",
    "wc": "5",
    "direction": "Đông Nam",
    "floor": "3",
    "front": "12",
    "legal": "Sổ hồng hoàn công",
    "loc": "Đường Đỗ Xuân Hợp, An Phú, TP. Thủ Đức",
    "type": "Bán",
    "cat": "nha-pho",
    "catName": "Nhà phố - Biệt thự",
    "projectCode": "the-global-city",
    "desc": "Căn biệt thự góc 2 mặt tiền hiếm hoi tại The Global City. Tầm view trực diện kênh đào nhạc nước.",
    "map": ""
  }
]